[
    {
        "question": "Some question 1",
        "answer": "2",
        "options": [
            "1",
            "2",
            "3"
        ]
    },
    {
        "question": "Some question 2",
        "answer": "2",
        "options": [
            "1",
            "2",
            "3"
        ]
    },
    {
        "question": "Some question 3",
        "answer": "2",
        "options": [
            "1",
            "2",
            "3"
        ]
    },
    {
        "question": "Some question 4",
        "answer": "2",
        "options": [
            "1",
            "2",
            "3"
        ]
    }
]